<?xml version="1.0" encoding="utf-8"?>
<ArrayOfEngineer xmlns:xsi="http://www.w3.org/2001/XMLSchema-instance" xmlns:xsd="http://www.w3.org/2001/XMLSchema">
  <Engineer>
    <Id>734607</Id>
    <Name>Yair Cohen</Name>
    <Email>yair.cohen@gmail.com</Email>
    <SalaryHour>2687623.787439035</SalaryHour>
    <Level>Beginner</Level>
    <IsActive>false</IsActive>
  </Engineer>
  <Engineer>
    <Id>22041992</Id>
    <Name>Dina Klein</Name>
    <Email>dina.klein@gmail.com</Email>
    <SalaryHour>9540827.759816315</SalaryHour>
    <Level>Expert</Level>
    <IsActive>false</IsActive>
  </Engineer>
  <Engineer>
    <Id>44634138</Id>
    <Name>Shira Israelof</Name>
    <Email>shira.israelof@gmail.com</Email>
    <SalaryHour>9167854.730778493</SalaryHour>
    <Level>Beginner</Level>
    <IsActive>false</IsActive>
  </Engineer>
  <Engineer>
    <Id>32043794</Id>
    <Name>Yael Cohen</Name>
    <Email>yael.cohen@gmail.com</Email>
    <SalaryHour>6328834.3567746645</SalaryHour>
    <Level>Intermediate</Level>
    <IsActive>false</IsActive>
  </Engineer>
  <Engineer>
    <Id>84249314</Id>
    <Name>Miri Levi</Name>
    <Email>miri.levi@gmail.com</Email>
    <SalaryHour>4835926.244831997</SalaryHour>
    <Level>AdvancedBeginner</Level>
    <IsActive>false</IsActive>
  </Engineer>
  <Engineer>
    <Id>36785850</Id>
    <Name>Dani Levi</Name>
    <Email>dani.levi@gmail.com</Email>
    <SalaryHour>262278.33352844854</SalaryHour>
    <Level>Intermediate</Level>
    <IsActive>false</IsActive>
  </Engineer>
  <Engineer>
    <Id>36147254</Id>
    <Name>Eli Amar</Name>
    <Email>eli.amar@gmail.com</Email>
    <SalaryHour>8181783.2191665955</SalaryHour>
    <Level>Intermediate</Level>
    <IsActive>false</IsActive>
  </Engineer>
  <Engineer>
    <Id>96160884</Id>
    <Name>Yair Cohen</Name>
    <Email>yair.cohen@gmail.com</Email>
    <SalaryHour>1225777.142015243</SalaryHour>
    <Level>Intermediate</Level>
    <IsActive>false</IsActive>
  </Engineer>
  <Engineer>
    <Id>53275549</Id>
    <Name>Shira Israelof</Name>
    <Email>shira.israelof@gmail.com</Email>
    <SalaryHour>8604249.40697293</SalaryHour>
    <Level>AdvancedBeginner</Level>
    <IsActive>false</IsActive>
  </Engineer>
  <Engineer>
    <Id>92647865</Id>
    <Name>Yael Cohen</Name>
    <Email>yael.cohen@gmail.com</Email>
    <SalaryHour>9673339.843563175</SalaryHour>
    <Level>Advanced</Level>
    <IsActive>false</IsActive>
  </Engineer>
  <Engineer>
    <Id>66820978</Id>
    <Name>Miri Levi</Name>
    <Email>miri.levi@gmail.com</Email>
    <SalaryHour>3785947.2018610365</SalaryHour>
    <Level>Beginner</Level>
    <IsActive>false</IsActive>
  </Engineer>
  <Engineer>
    <Id>10996620</Id>
    <Name>Dani Levi</Name>
    <Email>dani.levi@gmail.com</Email>
    <SalaryHour>5359282.379822208</SalaryHour>
    <Level>Beginner</Level>
    <IsActive>false</IsActive>
  </Engineer>
  <Engineer>
    <Id>38174271</Id>
    <Name>Eli Amar</Name>
    <Email>eli.amar@gmail.com</Email>
    <SalaryHour>98155267</SalaryHour>
    <Level>Expert</Level>
    <IsActive>false</IsActive>
  </Engineer>
  <Engineer>
    <Id>10945596</Id>
    <Name>Ariela Levi</Name>
    <Email>ariela.levin@gmail.com</Email>
    <SalaryHour>34</SalaryHour>
    <Level>AdvancedBeginner</Level>
    <IsActive>false</IsActive>
  </Engineer>
  <Engineer>
    <Id>326034865</Id>
    <Name>Yishay</Name>
    <Email>ishayshlomotiram@gmail.com</Email>
    <SalaryHour>3000000000</SalaryHour>
    <Level>AdvancedBeginner</Level>
    <IsActive>false</IsActive>
  </Engineer>
  <Engineer>
    <Id>79260901</Id>
    <Name>Dani Levi</Name>
    <Email>dani.levi@gmail.com</Email>
    <SalaryHour>6388697.328354261</SalaryHour>
    <Level>Intermediate</Level>
    <IsActive>false</IsActive>
  </Engineer>
  <Engineer>
    <Id>78766432</Id>
    <Name>Eli Amar</Name>
    <Email>eli.amar@gmail.com</Email>
    <SalaryHour>8741235.873643013</SalaryHour>
    <Level>Beginner</Level>
    <IsActive>false</IsActive>
  </Engineer>
  <Engineer>
    <Id>39777339</Id>
    <Name>Yair Cohen</Name>
    <Email>yair.cohen@gmail.com</Email>
    <SalaryHour>1090717.8937028747</SalaryHour>
    <Level>Advanced</Level>
    <IsActive>false</IsActive>
  </Engineer>
  <Engineer>
    <Id>82961459</Id>
    <Name>Ariela Levin</Name>
    <Email>ariela.levin@gmail.com</Email>
    <SalaryHour>8008932.47972188</SalaryHour>
    <Level>AdvancedBeginner</Level>
    <IsActive>false</IsActive>
  </Engineer>
  <Engineer>
    <Id>91568341</Id>
    <Name>Dina Klein</Name>
    <Email>dina.klein@gmail.com</Email>
    <SalaryHour>6993330.087898899</SalaryHour>
    <Level>Advanced</Level>
    <IsActive>false</IsActive>
  </Engineer>
  <Engineer>
    <Id>60717529</Id>
    <Name>Shira Israelof</Name>
    <Email>shira.israelof@gmail.com</Email>
    <SalaryHour>1373345.8450121544</SalaryHour>
    <Level>Advanced</Level>
    <IsActive>false</IsActive>
  </Engineer>
  <Engineer>
    <Id>91678432</Id>
    <Name>Yael Cohen</Name>
    <Email>yael.cohen@gmail.com</Email>
    <SalaryHour>1297353.5213642076</SalaryHour>
    <Level>Advanced</Level>
    <IsActive>false</IsActive>
  </Engineer>
  <Engineer>
    <Id>9385410</Id>
    <Name>Miri Levi</Name>
    <Email>miri.levi@gmail.com</Email>
    <SalaryHour>5206367.434231159</SalaryHour>
    <Level>Advanced</Level>
    <IsActive>false</IsActive>
  </Engineer>
  <Engineer>
    <Id>70115781</Id>
    <Name>Dani Levi</Name>
    <Email>dani.levi@gmail.com</Email>
    <SalaryHour>5100344.265279184</SalaryHour>
    <Level>Advanced</Level>
    <IsActive>false</IsActive>
  </Engineer>
  <Engineer>
    <Id>7870428</Id>
    <Name>Eli Amar</Name>
    <Email>eli.amar@gmail.com</Email>
    <SalaryHour>2796268.6910511144</SalaryHour>
    <Level>Intermediate</Level>
    <IsActive>false</IsActive>
  </Engineer>
  <Engineer>
    <Id>96905385</Id>
    <Name>Yair Cohen</Name>
    <Email>yair.cohen@gmail.com</Email>
    <SalaryHour>8754756.127435757</SalaryHour>
    <Level>Intermediate</Level>
    <IsActive>false</IsActive>
  </Engineer>
  <Engineer>
    <Id>84464191</Id>
    <Name>Ariela Levin</Name>
    <Email>ariela.levin@gmail.com</Email>
    <SalaryHour>4189349.0618522624</SalaryHour>
    <Level>AdvancedBeginner</Level>
    <IsActive>false</IsActive>
  </Engineer>
  <Engineer>
    <Id>25595535</Id>
    <Name>Dina Klein</Name>
    <Email>dina.klein@gmail.com</Email>
    <SalaryHour>218970.25460170186</SalaryHour>
    <Level>Beginner</Level>
    <IsActive>false</IsActive>
  </Engineer>
  <Engineer>
    <Id>11841270</Id>
    <Name>Shira Israelof</Name>
    <Email>shira.israelof@gmail.com</Email>
    <SalaryHour>444564.6106856685</SalaryHour>
    <Level>Beginner</Level>
    <IsActive>false</IsActive>
  </Engineer>
  <Engineer>
    <Id>96549803</Id>
    <Name>Yael Cohen</Name>
    <Email>yael.cohen@gmail.com</Email>
    <SalaryHour>7280823.844586211</SalaryHour>
    <Level>Advanced</Level>
    <IsActive>false</IsActive>
  </Engineer>
  <Engineer>
    <Id>90972654</Id>
    <Name>Miri Levi</Name>
    <Email>miri.levi@gmail.com</Email>
    <SalaryHour>3361259.8183614505</SalaryHour>
    <Level>Expert</Level>
    <IsActive>false</IsActive>
  </Engineer>
  <Engineer>
    <Id>39489783</Id>
    <Name>jbutf</Name>
    <Email>jhhh</Email>
    <SalaryHour>5146488.331846883</SalaryHour>
    <Level>Advanced</Level>
    <IsActive>false</IsActive>
  </Engineer>
  <Engineer>
    <Id>47050527</Id>
    <Name>Ariela Levin</Name>
    <Email>ariela.levin@gmail.com</Email>
    <SalaryHour>4368864</SalaryHour>
    <Level>Expert</Level>
    <IsActive>false</IsActive>
  </Engineer>
</ArrayOfEngineer>